{
	"info": {
		"_postman_id": "fe2c4ab4-d8a5-472d-b7b4-ae0c34506833",
		"name": "nest-js-book",
		"schema": "https://schema.getpostman.com/json/collection/v2.1.0/collection.json"
	},
	"item": [
		{
			"name": "users",
			"description": "",
			"item": [
				{
					"name": "Get Users",
					"request": {
						"method": "GET",
						"header": [],
						"body": {},
						"url": {
							"raw": "{{server}}/users",
							"host": [
								"{{server}}"
							],
							"path": [
								"users"
							]
						}
					},
					"response": []
				},
				{
					"name": "Create User",
					"request": {
						"method": "POST",
						"header": [
							{
								"key": "Content-Type",
								"value": "application/json"
							}
						],
						"body": {
							"mode": "raw",
							"raw": "{\n\t\"email\": \"jane.doe@gmail.com\",\n\t\"password\": \"P@ssw0rd\",\n\t\"firstName\": \"Jane\",\n\t\"lastName\": \"Doe\"\n}"
						},
						"url": {
							"raw": "{{server}}/users",
							"host": [
								"{{server}}"
							],
							"path": [
								"users"
							]
						}
					},
					"response": []
				},
				{
					"name": "Get User",
					"request": {
						"method": "GET",
						"header": [],
						"body": {},
						"url": {
							"raw": "{{server}}/users/1",
							"host": [
								"{{server}}"
							],
							"path": [
								"users",
								"1"
							]
						}
					},
					"response": []
				},
				{
					"name": "Update User",
					"request": {
						"method": "PUT",
						"header": [
							{
								"key": "Content-Type",
								"value": "application/json"
							}
						],
						"body": {
							"mode": "raw",
							"raw": "{\n\t\"birthday\": 315606530000\n}"
						},
						"url": {
							"raw": "{{server}}/users/1",
							"host": [
								"{{server}}"
							],
							"path": [
								"users",
								"1"
							]
						}
					},
					"response": []
				}
			],
			"event": [
				{
					"listen": "prerequest",
					"script": {
						"id": "88dc8903-b5ac-40ad-b66e-2f947c8f7dce",
						"type": "text/javascript",
						"exec": [
							""
						]
					}
				},
				{
					"listen": "test",
					"script": {
						"id": "fb6f40c0-d5b0-4980-8499-62a4d1b15f1c",
						"type": "text/javascript",
						"exec": [
							""
						]
					}
				}
			]
		},
		{
			"name": "authentication",
			"description": "",
			"item": [
				{
					"name": "Login",
					"event": [
						{
							"listen": "test",
							"script": {
								"id": "9d398ed9-f23e-44fc-8945-44d9c0c92874",
								"type": "text/javascript",
								"exec": [
									"const response = JSON.parse(responseBody);",
									"pm.environment.set(\"access_token\", response.access_token);"
								]
							}
						}
					],
					"request": {
						"method": "POST",
						"header": [
							{
								"key": "Content-Type",
								"value": "application/json"
							}
						],
						"body": {
							"mode": "raw",
							"raw": "{\n\t\"email\": \"jane.doe@gmail.com\",\n\t\"password\": \"P@ssw0rd\"\n}"
						},
						"url": {
							"raw": "{{server}}/login",
							"host": [
								"{{server}}"
							],
							"path": [
								"login"
							]
						}
					},
					"response": []
				}
			]
		},
		{
			"name": "entries",
			"description": "",
			"item": [
				{
					"name": "Get Entries",
					"request": {
						"method": "GET",
						"header": [],
						"body": {},
						"url": {
							"raw": "{{server}}/entries",
							"host": [
								"{{server}}"
							],
							"path": [
								"entries"
							]
						}
					},
					"response": []
				},
				{
					"name": "Create Entry",
					"request": {
						"method": "POST",
						"header": [
							{
								"key": "Content-Type",
								"value": "application/json"
							}
						],
						"body": {
							"mode": "raw",
							"raw": "{\n\t\"title\": \"Lorem ipsum dolor sit amet.\",\n\t\"content\": \"Lorem ipsum dolor sit amet, consectetur adipiscing elit. Vivamus ante dolor, ornare ac placerat nec, malesuada vel neque. Phasellus non ligula nunc. Nullam tincidunt odio eget tellus dignissim vulputate. Cras quis tempus nisi. Sed viverra ornare diam, sit amet molestie nunc facilisis ultricies. Cras rutrum dolor in nulla interdum, sit amet dapibus eros mattis. Nulla eget tempor enim. Sed efficitur sem eu sodales mattis. Cras at massa ultrices, convallis elit nec, interdum diam. Aliquam imperdiet dolor id turpis sagittis aliquet. Praesent laoreet felis sem, porttitor feugiat justo pulvinar et. Fusce nec purus nec dolor sagittis eleifend at sit amet eros. Vestibulum vel nibh eu felis finibus iaculis. Ut nec nisl purus. Maecenas a vestibulum purus, ut faucibus odio.\\nNulla varius urna vitae tortor consectetur, ut ultrices mi feugiat. Maecenas ultricies convallis nibh quis semper. Mauris elementum placerat suscipit. Aliquam interdum sapien in nisi pulvinar, vitae cursus erat mattis. Sed porttitor sem nec dictum luctus. Aliquam efficitur faucibus leo, vitae blandit arcu finibus id. Integer ornare metus sit amet tellus dapibus, ut blandit urna tristique. Nunc dignissim erat pulvinar ipsum pellentesque, vitae eleifend massa faucibus. Ut aliquet egestas turpis eu fermentum. Duis vel ullamcorper purus. Proin vel consequat erat. Phasellus nec viverra tortor, facilisis ullamcorper quam. Duis leo mauris, feugiat congue ornare vestibulum, pharetra at mauris. Nunc fermentum, lorem a pretium venenatis, ex nisl rutrum massa, nec porttitor turpis quam nec ligula.\\nQuisque fringilla elit pellentesque ante cursus condimentum. Morbi tristique nulla ac justo venenatis eleifend. Sed quis diam enim. Nunc venenatis ipsum a commodo interdum. Curabitur ac placerat sapien, in posuere odio. Sed vestibulum eros ac lacinia scelerisque. Pellentesque habitant morbi tristique senectus et netus et malesuada fames ac turpis egestas. Suspendisse ac aliquam nunc. Duis hendrerit sem a mi lacinia, imperdiet pellentesque risus blandit. Nulla facilisi. Vestibulum ante ipsum primis in faucibus orci luctus et ultrices posuere cubilia Curae;\\nCras sollicitudin maximus diam. Vestibulum nec nisl eros. Orci varius natoque penatibus et magnis dis parturient montes, nascetur ridiculus mus. Sed dignissim blandit turpis sed bibendum. Cras ante diam, pellentesque id quam vitae, sollicitudin posuere ligula. Nullam volutpat justo sed lectus mollis consectetur. Phasellus quis consectetur ligula, vel varius lorem. Etiam viverra ac ipsum vel suscipit.\"\n}"
						},
						"url": {
							"raw": "{{server}}/entries",
							"host": [
								"{{server}}"
							],
							"path": [
								"entries"
							]
						}
					},
					"response": []
				},
				{
					"name": "Get Entry",
					"request": {
						"method": "GET",
						"header": [],
						"body": {},
						"url": {
							"raw": "{{server}}/entries/1",
							"host": [
								"{{server}}"
							],
							"path": [
								"entries",
								"1"
							]
						}
					},
					"response": []
				},
				{
					"name": "Update Entry",
					"request": {
						"method": "PUT",
						"header": [
							{
								"key": "Content-Type",
								"value": "application/json"
							}
						],
						"body": {
							"mode": "raw",
							"raw": "{\n\t\"title\": \"Changing the title\",\n\t\"content\": \"Changing the content\"\n}"
						},
						"url": {
							"raw": "{{server}}/entries/1",
							"host": [
								"{{server}}"
							],
							"path": [
								"entries",
								"1"
							]
						}
					},
					"response": []
				},
				{
					"name": "Delete Entry",
					"request": {
						"method": "DELETE",
						"header": [],
						"body": {},
						"url": {
							"raw": "{{server}}/entries/1",
							"host": [
								"{{server}}"
							],
							"path": [
								"entries",
								"1"
							]
						}
					},
					"response": []
				}
			]
		},
		{
			"name": "comments",
			"description": "",
			"item": [
				{
					"name": "Get Comments",
					"request": {
						"method": "GET",
						"header": [],
						"body": {},
						"url": {
							"raw": "{{server}}/entries/2/comments",
							"host": [
								"{{server}}"
							],
							"path": [
								"entries",
								"2",
								"comments"
							]
						}
					},
					"response": []
				},
				{
					"name": "Create Comment",
					"request": {
						"method": "POST",
						"header": [
							{
								"key": "Content-Type",
								"value": "application/json"
							}
						],
						"body": {
							"mode": "raw",
							"raw": "{\n\t\"body\": \"Lorem ipsum dolor sit amet, consectetur adipiscing elit. Pellentesque efficitur maximus sem vel posuere. Maecenas ultricies libero nec dui mattis fermentum. Curabitur eu est sed justo imperdiet venenatis. Proin consequat maximus lorem, non posuere metus auctor in. Suspendisse at purus a quam semper posuere. Quisque tristique fermentum ornare. In id ex eleifend ante eleifend euismod. Proin scelerisque, justo ut consequat tincidunt, dui mi viverra nibh, vitae aliquet ex diam commodo ligula. Suspendisse pretium volutpat mauris, et euismod lacus rhoncus id. Curabitur est lorem, vulputate sit amet faucibus vel, finibus non turpis. Nullam sit amet lacus vitae quam venenatis dictum. Nulla porttitor odio eget faucibus semper. Cras quis tortor nunc. Mauris at consectetur nulla. Ut consequat, mi eget aliquet ullamcorper, diam neque egestas mauris, in volutpat sapien neque ut dolor. Sed eu volutpat elit, ut volutpat erat.\"\n}"
						},
						"url": {
							"raw": "{{server}}/entries/2/comments",
							"host": [
								"{{server}}"
							],
							"path": [
								"entries",
								"2",
								"comments"
							]
						}
					},
					"response": []
				},
				{
					"name": "Get Comment",
					"request": {
						"method": "GET",
						"header": [],
						"body": {},
						"url": {
							"raw": "{{server}}/entries/2/comments/1",
							"host": [
								"{{server}}"
							],
							"path": [
								"entries",
								"2",
								"comments",
								"1"
							]
						}
					},
					"response": []
				},
				{
					"name": "Update Comment",
					"request": {
						"method": "PUT",
						"header": [
							{
								"key": "Content-Type",
								"value": "application/json"
							}
						],
						"body": {
							"mode": "raw",
							"raw": "{\n\t\"body\": \"Changing the body\"\n}"
						},
						"url": {
							"raw": "{{server}}/entries/2/comments/1",
							"host": [
								"{{server}}"
							],
							"path": [
								"entries",
								"2",
								"comments",
								"1"
							]
						}
					},
					"response": []
				},
				{
					"name": "Delete Comment",
					"request": {
						"method": "DELETE",
						"header": [],
						"body": {},
						"url": {
							"raw": "{{server}}/entries/2/comments/1",
							"host": [
								"{{server}}"
							],
							"path": [
								"entries",
								"2",
								"comments",
								"1"
							]
						}
					},
					"response": []
				}
			]
		}
	],
	"auth": {
		"type": "bearer",
		"bearer": [
			{
				"key": "token",
				"value": "{{access_token}}",
				"type": "string"
			}
		]
	},
	"event": [
		{
			"listen": "prerequest",
			"script": {
				"id": "cb1e3328-a461-46c9-b48d-691e65a031a3",
				"type": "text/javascript",
				"exec": [
					""
				]
			}
		},
		{
			"listen": "test",
			"script": {
				"id": "b4df42a6-0c6a-4f7c-891c-3ec7a75c883c",
				"type": "text/javascript",
				"exec": [
					""
				]
			}
		}
	]
}